analog/__init__.py
analog/analyzer.py
analog/exceptions.py
analog/formats.py
analog/main.py
analog/renderers.py
analog/report.py
analog/statistics.py
analog/utils.py
analog/tests/__init__.py
analog/tests/test_analyzer.py
analog/tests/test_formats.py
analog/tests/test_main.py
analog/tests/test_renderers.py
analog/tests/test_report.py
analog/tests/test_utils.py
analog-1.0.0.dist-info/DESCRIPTION.rst
analog-1.0.0.dist-info/entry_points.txt
analog-1.0.0.dist-info/METADATA
analog-1.0.0.dist-info/metadata.json
analog-1.0.0.dist-info/RECORD
analog-1.0.0.dist-info/top_level.txt
analog-1.0.0.dist-info/WHEEL
